{"nodes": [{"id": "leaves", "label": "leaves.js", "file_type": "code", "source_file": "src\\particles\\leaves.js", "source_location": "L1"}, {"id": "leaves_setleafwind", "label": "setLeafWind()", "file_type": "code", "source_file": "src\\particles\\leaves.js", "source_location": "L23"}, {"id": "leaves_initleaves", "label": "initLeaves()", "file_type": "code", "source_file": "src\\particles\\leaves.js", "source_location": "L25"}, {"id": "leaves_spawnleaf", "label": "spawnLeaf()", "file_type": "code", "source_file": "src\\particles\\leaves.js", "source_location": "L58"}, {"id": "leaves_updateleaves", "label": "updateLeaves()", "file_type": "code", "source_file": "src\\particles\\leaves.js", "source_location": "L84"}], "edges": [{"source": "leaves", "target": "three", "relation": "imports_from", "confidence": "EXTRACTED", "source_file": "src\\particles\\leaves.js", "source_location": "L1", "weight": 1.0}, {"source": "leaves", "target": "constants_js", "relation": "imports_from", "confidence": "EXTRACTED", "source_file": "src\\particles\\leaves.js", "source_location": "L2", "weight": 1.0}, {"source": "leaves", "target": "renderer_js", "relation": "imports_from", "confidence": "EXTRACTED", "source_file": "src\\particles\\leaves.js", "source_location": "L3", "weight": 1.0}, {"source": "leaves", "target": "rng_js", "relation": "imports_from", "confidence": "EXTRACTED", "source_file": "src\\particles\\leaves.js", "source_location": "L4", "weight": 1.0}, {"source": "leaves", "target": "leaves_setleafwind", "relation": "contains", "confidence": "EXTRACTED", "source_file": "src\\particles\\leaves.js", "source_location": "L23", "weight": 1.0}, {"source": "leaves", "target": "leaves_initleaves", "relation": "contains", "confidence": "EXTRACTED", "source_file": "src\\particles\\leaves.js", "source_location": "L25", "weight": 1.0}, {"source": "leaves", "target": "leaves_spawnleaf", "relation": "contains", "confidence": "EXTRACTED", "source_file": "src\\particles\\leaves.js", "source_location": "L58", "weight": 1.0}, {"source": "leaves", "target": "leaves_updateleaves", "relation": "contains", "confidence": "EXTRACTED", "source_file": "src\\particles\\leaves.js", "source_location": "L84", "weight": 1.0}]}