{"nodes": [{"id": "orbs", "label": "orbs.js", "file_type": "code", "source_file": "src\\entities\\magical\\orbs.js", "source_location": "L1"}, {"id": "orbs_makeorb", "label": "makeOrb()", "file_type": "code", "source_file": "src\\entities\\magical\\orbs.js", "source_location": "L14"}], "edges": [{"source": "orbs", "target": "three", "relation": "imports_from", "confidence": "EXTRACTED", "source_file": "src\\entities\\magical\\orbs.js", "source_location": "L9", "weight": 1.0}, {"source": "orbs", "target": "renderer_js", "relation": "imports_from", "confidence": "EXTRACTED", "source_file": "src\\entities\\magical\\orbs.js", "source_location": "L10", "weight": 1.0}, {"source": "orbs", "target": "constants_js", "relation": "imports_from", "confidence": "EXTRACTED", "source_file": "src\\entities\\magical\\orbs.js", "source_location": "L11", "weight": 1.0}, {"source": "orbs", "target": "rng_js", "relation": "imports_from", "confidence": "EXTRACTED", "source_file": "src\\entities\\magical\\orbs.js", "source_location": "L12", "weight": 1.0}, {"source": "orbs", "target": "orbs_makeorb", "relation": "contains", "confidence": "EXTRACTED", "source_file": "src\\entities\\magical\\orbs.js", "source_location": "L14", "weight": 1.0}]}